ML_Utility/ML_package.py
ML_Utility/__init__.py
mlpkg-0.3.dist-info/LICENSE.TXT
mlpkg-0.3.dist-info/METADATA
mlpkg-0.3.dist-info/WHEEL
mlpkg-0.3.dist-info/top_level.txt
mlpkg-0.3.dist-info/RECORD
