Metadata-Version: 2.1
Name: mlpkg
Version: 0.3
Summary: ML package
Home-page: https://https://github.com/Sakshi-agarwal8/DeepLeaning
Author: Sakshi Agarwal
Author-email: sakshi.agg23@gmail.com
License: MIT
Platform: UNKNOWN
Requires-Dist: numpy (>=1.18.5)
Requires-Dist: pandas (>=1.0.5)
Requires-Dist: scikit-learn (>=0.23.1)
